{
    "id": 985,
    "name": "Arcturus Remake",
    "author": "kartel",
    "creators": ["M336", "kartel"],
    "verifier": "kartel",
    "verification": "https://youtu.be/Od0IRKoH2zI?si=8lgqmEfETbuhU8Gn",
    "percentToQualify": "50",
    "password": "Free To Copy",
    "records": [
        {
            "user": "flo.wer",
            "link": "https://www.youtube.com/watch?v=REehPZOoDFk",
            "percent": 100,
            "hz": 240
        },
        {
            "user": "Kyy",
            "link": "https://www.youtube.com/watch?v=8E98ffHGzXU",
            "percent": 100,
            "hz": 240
        }
    ]
}
